pytest_factory/__init__.py
pytest_factory/factory_fixtures.py
pytest_factory/lazy_fixture.py
pytest_factory/plugin.py
pytest_factory-0.0.1.dev0.dist-info/entry_points.txt
pytest_factory-0.0.1.dev0.dist-info/LICENSE
pytest_factory-0.0.1.dev0.dist-info/WHEEL
pytest_factory-0.0.1.dev0.dist-info/METADATA
pytest_factory-0.0.1.dev0.dist-info/RECORD
